pymirai/Message.py
pymirai/Mirailib.py
pymirai/Network.py
pymirai/__init__.py
pymirai-0.0.4.6.dist-info/LICENSE
pymirai-0.0.4.6.dist-info/METADATA
pymirai-0.0.4.6.dist-info/WHEEL
pymirai-0.0.4.6.dist-info/top_level.txt
pymirai-0.0.4.6.dist-info/RECORD
