Metadata-Version: 2.1
Name: pymirai
Version: 0.0.4.6
Summary: A simple python binding for the great project Mirai
Home-page: https://github.com/0h2o/pymirai
Author: 0h2o
Author-email: yype@foxmail.com
License: UNKNOWN
Platform: UNKNOWN
Classifier: Programming Language :: Python :: 3
Classifier: License :: OSI Approved :: GNU Affero General Public License v3 or later (AGPLv3+)
Classifier: Operating System :: OS Independent
Requires-Python: >=3.7.1
Requires-Dist: aiohttp (>=3.6.2)
